font_fetcher/__init__.py
font_fetcher/misc.py
font_fetcher/ocp.py
font_fetcher/ocp_test.py
font_fetcher/repo.py
font_fetcher/repo_1001fonts.py
font_fetcher/repo_common.py
font_fetcher/repo_registry.py
font_fetcher/repo_test.py
font_fetcher-0.0.5.dist-info/METADATA
font_fetcher-0.0.5.dist-info/WHEEL
font_fetcher-0.0.5.dist-info/RECORD
