Metadata-Version: 2.4
Name: font-fetcher
Version: 0.0.5
Summary: 
Author: Yeicor
Author-email: 4929005+Yeicor@users.noreply.github.com
Requires-Python: >=3.10,<3.13
Classifier: Programming Language :: Python :: 3
Classifier: Programming Language :: Python :: 3.10
Classifier: Programming Language :: Python :: 3.11
Classifier: Programming Language :: Python :: 3.12
Requires-Dist: beautifulsoup4 (>=4.13.4,<5.0.0)
Requires-Dist: requests (>=2.32.4,<3.0.0)
